README
setup.py
roxee/__init__.py
roxee/exceptions.py
roxee/roxee.py
roxee.egg-info/PKG-INFO
roxee.egg-info/SOURCES.txt
roxee.egg-info/dependency_links.txt
roxee.egg-info/requires.txt
roxee.egg-info/top_level.txt
roxee.egg-info/zip-safe