Metadata-Version: 1.0
Name: roxee
Version: 0.0.1
Summary: Roxee API v1.0
Home-page: https://github.com/webitup/python-roxee
Author: Emmanuel Tabard
Author-email: manu@webitup.fr
License: UNKNOWN
Download-URL: http://pypi.python.org/pypi/roxee/
Keywords: roxee
Platform: UNKNOWN
Classifier: Development Status :: 5 - Production/Stable
Classifier: Intended Audience :: Developers
Classifier: License :: OSI Approved :: MIT License
Classifier: Natural Language :: English
Classifier: Operating System :: OS Independent
Classifier: Programming Language :: Python
Classifier: Programming Language :: Python
Classifier: Programming Language :: Python :: 2.6
Classifier: Programming Language :: Python :: 2.7
Classifier: Programming Language :: Python :: 3
Classifier: Programming Language :: Python :: 3.0
Classifier: Programming Language :: Python :: 3.1
Classifier: Programming Language :: Python :: 3.2
